kraken_exchange/__init__.py
kraken_exchange/kraken_exchange.py
kraken_exchange-0.0.5.dist-info/LICENSE
kraken_exchange-0.0.5.dist-info/METADATA
kraken_exchange-0.0.5.dist-info/WHEEL
kraken_exchange-0.0.5.dist-info/top_level.txt
kraken_exchange-0.0.5.dist-info/RECORD
