Metadata-Version: 2.2
Name: kraken-exchange
Version: 0.0.5
Summary: A simple package for connecting to the the Kraken API.
Author-email: Nikhil Sunder <nsunder724@gmail.com>
Maintainer-email: Nikhil Sunder <nsunder724@gmail.com>
License:                     GNU GENERAL PUBLIC LICENSE
Project-URL: Repository, https://github.com/nikhilxsunder/kraken-exchange
Project-URL: Issues, https://github.com/nikhilxsunder/kraken-exchange/issues
Project-URL: Documentation, https://docs.kraken.com/api/
Keywords: kraken,crypto,api,finance,kraken api
Classifier: Programming Language :: Python :: 3
Classifier: License :: OSI Approved :: GNU Affero General Public License v3
Classifier: Operating System :: OS Independent
Classifier: Development Status :: 4 - Beta
Classifier: Intended Audience :: Financial and Insurance Industry
Classifier: Topic :: Office/Business :: Financial :: Investment
Requires-Python: >=3.8
License-File: LICENSE
Requires-Dist: requests
